Workbook

Sheet Menu Matrix
B2: Ember Table Menu Engineering Studio
B5: Item | C5: Popularity | D5: Contribution
B6: Charred Carrot | C6: 44 | D6: 18 | G6: 50 | H6: 10 | J6: 10 | K6: 25
B7: Lamb Flatbread | C7: 68 | D7: 28 | G7: 50 | H7: 42 | J7: 80 | K7: 25
B8: Citrus Cod | C8: 32 | D8: 31
B9: Miso Potatoes | C9: 72 | D9: 16
B10: Duck Ragu | C10: 25 | D10: 34
B11: Market Tart | C11: 40 | D11: 22
B12: Steak Frites | C12: 58 | D12: 39
B13: Herb Gnocchi | C13: 20 | D13: 19
H14: STARS
B15: PLOWHORSES Popular · lower margin
B18: DOGS Lower popularity · lower margin
B21: PUZZLES Lower popularity · higher margin
B24: STARS Popular · higher margin
H31: PUZZLES

Sheet Recipe Costing
A2: Dish | B2: Menu Price | C2: Ingredient Cost | D2: Food Cost % | E2: Contribution Margin | F2: Recommended Action
A3: Charred Carrot | B3: 45 | C3: 7.56 | D3: =C3/B3 | E3: =B3-C3 | F3: =IF(D3>0.35,"Reprice",IF(E3>45,"Feature","Monitor"))
A4: Lamb Flatbread | B4: 70 | C4: 11.76 | D4: =C4/B4 | E4: =B4-C4 | F4: =IF(D4>0.35,"Reprice",IF(E4>45,"Feature","Monitor"))
A5: Citrus Cod | B5: 77.5 | C5: 13.02 | D5: =C5/B5 | E5: =B5-C5 | F5: =IF(D5>0.35,"Reprice",IF(E5>45,"Feature","Monitor"))
A6: Miso Potatoes | B6: 40 | C6: 6.72 | D6: =C6/B6 | E6: =B6-C6 | F6: =IF(D6>0.35,"Reprice",IF(E6>45,"Feature","Monitor"))
A7: Duck Ragu | B7: 85 | C7: 14.28 | D7: =C7/B7 | E7: =B7-C7 | F7: =IF(D7>0.35,"Reprice",IF(E7>45,"Feature","Monitor"))
A8: Market Tart | B8: 55 | C8: 9.24 | D8: =C8/B8 | E8: =B8-C8 | F8: =IF(D8>0.35,"Reprice",IF(E8>45,"Feature","Monitor"))
A9: Steak Frites | B9: 97.5 | C9: 16.38 | D9: =C9/B9 | E9: =B9-C9 | F9: =IF(D9>0.35,"Reprice",IF(E9>45,"Feature","Monitor"))
A10: Herb Gnocchi | B10: 47.5 | C10: 7.98 | D10: =C10/B10 | E10: =B10-C10 | F10: =IF(D10>0.35,"Reprice",IF(E10>45,"Feature","Monitor"))

Sheet Sales Mix
A2: Dish | B2: Covers | C2: Revenue
A3: Charred Carrot | B3: 176 | C3: =B3*INDEX('Recipe Costing'!B:B,MATCH(A3,'Recipe Costing'!A:A,0))
A4: Lamb Flatbread | B4: 272 | C4: =B4*INDEX('Recipe Costing'!B:B,MATCH(A4,'Recipe Costing'!A:A,0))
A5: Citrus Cod | B5: 128 | C5: =B5*INDEX('Recipe Costing'!B:B,MATCH(A5,'Recipe Costing'!A:A,0))
A6: Miso Potatoes | B6: 288 | C6: =B6*INDEX('Recipe Costing'!B:B,MATCH(A6,'Recipe Costing'!A:A,0))
A7: Duck Ragu | B7: 100 | C7: =B7*INDEX('Recipe Costing'!B:B,MATCH(A7,'Recipe Costing'!A:A,0))
A8: Market Tart | B8: 160 | C8: =B8*INDEX('Recipe Costing'!B:B,MATCH(A8,'Recipe Costing'!A:A,0))
A9: Steak Frites | B9: 232 | C9: =B9*INDEX('Recipe Costing'!B:B,MATCH(A9,'Recipe Costing'!A:A,0))
A10: Herb Gnocchi | B10: 80 | C10: =B10*INDEX('Recipe Costing'!B:B,MATCH(A10,'Recipe Costing'!A:A,0))
