Workbook
Name Scenario_Selected: 'Assumptions'!$B$4
Name Forecast_Start: 'Assumptions'!$E$5

Sheet Summary
A1: Fieldnote Works — Cash-Flow Dashboard
A3: Active scenario | B3: =Scenario_Selected | D3: Model status | E3: =Checks!B10
A5: Opening cash | B5: ='13-Week Forecast'!B4
A6: 13-week receipts | B6: =SUM('13-Week Forecast'!B5:N5)+SUM('13-Week Forecast'!B10:N10)
A7: 13-week outflows | B7: =SUM('13-Week Forecast'!B6:N9)+SUM('13-Week Forecast'!B11:N11)
A8: Ending cash | B8: ='13-Week Forecast'!N13
A9: Minimum cash | B9: =MIN('13-Week Forecast'!B13:N13)
A10: Ending runway | B10: ='13-Week Forecast'!N14
A11: Worst weekly status | B11: =IF(COUNTIF('13-Week Forecast'!B15:N15,"Critical")>0,"Critical",IF(COUNTIF('13-Week Forecast'!B15:N15,"At Risk")>0,"At Risk",IF(COUNTIF('13-Week Forecast'!B15:N15,"Watch")>0,"Watch","Healthy")))
A14: Cash balance trend

Sheet Assumptions
A1: Fieldnote Works — 13-Week Cash-Flow Forecast
A3: Input / Control | B3: Base | C3: Cautious | D3: Stretch | E3: Active | F3: Notes
A4: Scenario selected | B4: Base | F4: Use dropdown: Base, Cautious, Stretch
A5: Forecast start date | B5: 46244 | E5: =B5 | F5: Monday week start
A6: Opening cash | B6: 28500 | C6: 24000 | D6: 32000 | E6: =INDEX(B6:D6,1,MATCH($B$4,$B$20:$D$20,0)) | F6: Cash available at start of Week 1
A7: Minimum cash buffer | B7: 12000 | C7: 14000 | D7: 10000 | E7: =INDEX(B7:D7,1,MATCH($B$4,$B$20:$D$20,0)) | F7: Below this threshold = At Risk
A8: Weekly fixed expenses | B8: 3650 | C8: 3650 | D8: 3650 | E8: =INDEX(B8:D8,1,MATCH($B$4,$B$20:$D$20,0)) | F8: Tools, contractor retainers, hosting, insurance, rent
A9: Variable expense rate | B9: 0.18 | C9: 0.16 | D9: 0.22 | E9: =INDEX(B9:D9,1,MATCH($B$4,$B$20:$D$20,0)) | F9: As % of receipts
A10: Tax reserve rate | B10: 0.25 | C10: 0.25 | D10: 0.25 | E10: =INDEX(B10:D10,1,MATCH($B$4,$B$20:$D$20,0)) | F10: Reserve against receipts less variable costs
A11: Owner draw / week | B11: 1800 | C11: 1500 | D11: 2200 | E11: =INDEX(B11:D11,1,MATCH($B$4,$B$20:$D$20,0)) | F11: Planned owner distribution
A12: Starting pipeline receipts W1 | B12: 8200 | C12: 6000 | D12: 9500 | E12: =INDEX(B12:D12,1,MATCH($B$4,$B$20:$D$20,0)) | F12: Recurring + expected project cash receipts
A13: Weekly receipt growth | B13: 0.03 | C13: -0.02 | D13: 0.06 | E13: =INDEX(B13:D13,1,MATCH($B$4,$B$20:$D$20,0)) | F13: Scenario receipt trend
A14: Collection timing adjustment | B14: 1 | C14: 0.85 | D14: 1.12 | E14: =INDEX(B14:D14,1,MATCH($B$4,$B$20:$D$20,0)) | F14: Applies to expected receipts
A15: One-time receipt W4 | B15: 4500 | C15: 0 | D15: 6500 | E15: =INDEX(B15:D15,1,MATCH($B$4,$B$20:$D$20,0)) | F15: Example launch/payment milestone
A16: One-time expense W7 | B16: 3000 | C16: 4500 | D16: 2500 | E16: =INDEX(B16:D16,1,MATCH($B$4,$B$20:$D$20,0)) | F16: Example equipment/legal/contractor spike
A17: Runway warning threshold (weeks) | B17: 8 | C17: 10 | D17: 6 | E17: =INDEX(B17:D17,1,MATCH($B$4,$B$20:$D$20,0)) | F17: Displayed on Summary
B20: Base | C20: Cautious | D20: Stretch

Sheet 13-Week Forecast
A1: 13-Week Forecast
A3: Line Item | B3: =Forecast_Start+0 | C3: =Forecast_Start+7 | D3: =Forecast_Start+14 | E3: =Forecast_Start+21 | F3: =Forecast_Start+28 | G3: =Forecast_Start+35 | H3: =Forecast_Start+42 | I3: =Forecast_Start+49 | J3: =Forecast_Start+56 | K3: =Forecast_Start+63 | L3: =Forecast_Start+70 | M3: =Forecast_Start+77 | N3: =Forecast_Start+84
A4: Opening cash | B4: =Assumptions!$E$6 | C4: =B13 | D4: =C13 | E4: =D13 | F4: =E13 | G4: =F13 | H4: =G13 | I4: =H13 | J4: =I13 | ... N4: =M13
A5: Expected receipts | B5: =Assumptions!$E$12*POWER(1+Assumptions!$E$13,0)*Assumptions!$E$14 | C5: =Assumptions!$E$12*POWER(1+Assumptions!$E$13,1)*Assumptions!$E$14 | D5: =Assumptions!$E$12*POWER(1+Assumptions!$E$13,2)*Assumptions!$E$14 | E5: =Assumptions!$E$12*POWER(1+Assumptions!$E$13,3)*Assumptions!$E$14 | F5: =Assumptions!$E$12*POWER(1+Assumptions!$E$13,4)*Assumptions!$E$14 | G5: =Assumptions!$E$12*POWER(1+Assumptions!$E$13,5)*Assumptions!$E$14 | H5: =Assumptions!$E$12*POWER(1+Assumptions!$E$13,6)*Assumptions!$E$14 | I5: =Assumptions!$E$12*POWER(1+Assumptions!$E$13,7)*Assumptions!$E$14 | J5: =Assumptions!$E$12*POWER(1+Assumptions!$E$13,8)*Assumptions!$E$14 | K5: =Assumptions!$E$12*POWER(1+Assumptions!$E$13,9)*Assumptions!$E$14 | L5: =Assumptions!$E$12*POWER(1+Assumptions!$E$13,10)*Assumptions!$E$14 | M5: =Assumptions!$E$12*POWER(1+Assumptions!$E$13,11)*Assumptions!$E$14 | N5: =Assumptions!$E$12*POWER(1+Assumptions!$E$13,12)*Assumptions!$E$14
A6: Fixed expenses | B6: =Assumptions!$E$8 | C6: =Assumptions!$E$8 | D6: =Assumptions!$E$8 | E6: =Assumptions!$E$8 | F6: =Assumptions!$E$8 | G6: =Assumptions!$E$8 | H6: =Assumptions!$E$8 | I6: =Assumptions!$E$8 | ... N6: =Assumptions!$E$8
A7: Variable expenses | B7: =B5*Assumptions!$E$9 | C7: =C5*Assumptions!$E$9 | D7: =D5*Assumptions!$E$9 | E7: =E5*Assumptions!$E$9 | F7: =F5*Assumptions!$E$9 | G7: =G5*Assumptions!$E$9 | H7: =H5*Assumptions!$E$9 | I7: =I5*Assumptions!$E$9 | ... N7: =N5*Assumptions!$E$9
A8: Tax reserve | B8: =MAX(0,(B5-B7)*Assumptions!$E$10) | C8: =MAX(0,(C5-C7)*Assumptions!$E$10) | D8: =MAX(0,(D5-D7)*Assumptions!$E$10) | E8: =MAX(0,(E5-E7)*Assumptions!$E$10) | F8: =MAX(0,(F5-F7)*Assumptions!$E$10) | G8: =MAX(0,(G5-G7)*Assumptions!$E$10) | H8: =MAX(0,(H5-H7)*Assumptions!$E$10) | I8: =MAX(0,(I5-I7)*Assumptions!$E$10) | ... N8: =MAX(0,(N5-N7)*Assumptions!$E$10)
A9: Owner draw | B9: =Assumptions!$E$11 | C9: =Assumptions!$E$11 | D9: =Assumptions!$E$11 | E9: =Assumptions!$E$11 | F9: =Assumptions!$E$11 | G9: =Assumptions!$E$11 | H9: =Assumptions!$E$11 | I9: =Assumptions!$E$11 | ... N9: =Assumptions!$E$11
A10: One-time receipts | B10: =0 | C10: =0 | D10: =0 | E10: =Assumptions!$E$15 | F10: =0 | G10: =0 | H10: =0 | I10: =0 | J10: =0 | K10: =0 | L10: =0 | M10: =0 | N10: =0
A11: One-time expenses | B11: =0 | C11: =0 | D11: =0 | E11: =0 | F11: =0 | G11: =0 | H11: =Assumptions!$E$16 | I11: =0 | J11: =0 | K11: =0 | L11: =0 | M11: =0 | N11: =0
A12: Net cash flow | B12: =B5+B10-B6-B7-B8-B9-B11 | C12: =C5+C10-C6-C7-C8-C9-C11 | D12: =D5+D10-D6-D7-D8-D9-D11 | E12: =E5+E10-E6-E7-E8-E9-E11 | F12: =F5+F10-F6-F7-F8-F9-F11 | G12: =G5+G10-G6-G7-G8-G9-G11 | H12: =H5+H10-H6-H7-H8-H9-H11 | I12: =I5+I10-I6-I7-I8-I9-I11 | ... N12: =N5+N10-N6-N7-N8-N9-N11
A13: Closing cash | B13: =B4+B12 | C13: =C4+C12 | D13: =D4+D12 | E13: =E4+E12 | F13: =F4+F12 | G13: =G4+G12 | H13: =H4+H12 | I13: =I4+I12 | ... N13: =N4+N12
A14: Runway (weeks) | B14: =IF((B6+B7+B8+B9)=0,999,B13/(B6+B7+B8+B9)) | C14: =IF((C6+C7+C8+C9)=0,999,C13/(C6+C7+C8+C9)) | D14: =IF((D6+D7+D8+D9)=0,999,D13/(D6+D7+D8+D9)) | E14: =IF((E6+E7+E8+E9)=0,999,E13/(E6+E7+E8+E9)) | F14: =IF((F6+F7+F8+F9)=0,999,F13/(F6+F7+F8+F9)) | G14: =IF((G6+G7+G8+G9)=0,999,G13/(G6+G7+G8+G9)) | H14: =IF((H6+H7+H8+H9)=0,999,H13/(H6+H7+H8+H9)) | I14: =IF((I6+I7+I8+I9)=0,999,I13/(I6+I7+I8+I9)) | ... N14: =IF((N6+N7+N8+N9)=0,999,N13/(N6+N7+N8+N9))
A15: Weekly risk status | B15: =IF(B13<Assumptions!$E$6*0.1,"Critical",IF(B13<Assumptions!$E$7,"At Risk",IF(B14<Assumptions!$E$17,"Watch","Healthy"))) | C15: =IF(C13<Assumptions!$E$6*0.1,"Critical",IF(C13<Assumptions!$E$7,"At Risk",IF(C14<Assumptions!$E$17,"Watch","Healthy"))) | D15: =IF(D13<Assumptions!$E$6*0.1,"Critical",IF(D13<Assumptions!$E$7,"At Risk",IF(D14<Assumptions!$E$17,"Watch","Healthy"))) | E15: =IF(E13<Assumptions!$E$6*0.1,"Critical",IF(E13<Assumptions!$E$7,"At Risk",IF(E14<Assumptions!$E$17,"Watch","Healthy"))) | F15: =IF(F13<Assumptions!$E$6*0.1,"Critical",IF(F13<Assumptions!$E$7,"At Risk",IF(F14<Assumptions!$E$17,"Watch","Healthy"))) | G15: =IF(G13<Assumptions!$E$6*0.1,"Critical",IF(G13<Assumptions!$E$7,"At Risk",IF(G14<Assumptions!$E$17,"Watch","Healthy"))) | H15: =IF(H13<Assumptions!$E$6*0.1,"Critical",IF(H13<Assumptions!$E$7,"At Risk",IF(H14<Assumptions!$E$17,"Watch","Healthy"))) | I15: =IF(I13<Assumptions!$E$6*0.1,"Critical",IF(I13<Assumptions!$E$7,"At Risk",IF(I14<Assumptions!$E$17,"Watch","Healthy"))) | ... N15: =IF(N13<Assumptions!$E$6*0.1,"Critical",IF(N13<Assumptions!$E$7,"At Risk",IF(N14<Assumptions!$E$17,"Watch","Healthy")))

Sheet Scenarios
A1: Scenario Comparison
A3: Metric | B3: Base | C3: Cautious | D3: Stretch | E3: Notes
A4: Opening cash | B4: =Assumptions!B$6 | C4: =Assumptions!C$6 | D4: =Assumptions!D$6 | E4: Scenario columns use their own assumptions
A5: Total receipts | B5: =SUMPRODUCT(Assumptions!B$12*POWER(1+Assumptions!B$13,COLUMN($A:$M)-1)*Assumptions!B$14)+Assumptions!B$15 | C5: =SUMPRODUCT(Assumptions!C$12*POWER(1+Assumptions!C$13,COLUMN($A:$M)-1)*Assumptions!C$14)+Assumptions!C$15 | D5: =SUMPRODUCT(Assumptions!D$12*POWER(1+Assumptions!D$13,COLUMN($A:$M)-1)*Assumptions!D$14)+Assumptions!D$15
A6: Total outflows | B6: =13*(Assumptions!B$8+Assumptions!B$11)+Assumptions!B$9*SUMPRODUCT(Assumptions!B$12*POWER(1+Assumptions!B$13,COLUMN($A:$M)-1)*Assumptions!B$14)+Assumptions!B$10*(SUMPRODUCT(Assumptions!B$12*POWER(1+Assumptions!B$13,COLUMN($A:$M)-1)*Assumptions!B$14)*(1-Assumptions!B$9))+Assumptions!B$16 | C6: =13*(Assumptions!C$8+Assumptions!C$11)+Assumptions!C$9*SUMPRODUCT(Assumptions!C$12*POWER(1+Assumptions!C$13,COLUMN($A:$M)-1)*Assumptions!C$14)+Assumptions!C$10*(SUMPRODUCT(Assumptions!C$12*POWER(1+Assumptions!C$13,COLUMN($A:$M)-1)*Assumptions!C$14)*(1-Assumptions!C$9))+Assumptions!C$16 | D6: =13*(Assumptions!D$8+Assumptions!D$11)+Assumptions!D$9*SUMPRODUCT(Assumptions!D$12*POWER(1+Assumptions!D$13,COLUMN($A:$M)-1)*Assumptions!D$14)+Assumptions!D$10*(SUMPRODUCT(Assumptions!D$12*POWER(1+Assumptions!D$13,COLUMN($A:$M)-1)*Assumptions!D$14)*(1-Assumptions!D$9))+Assumptions!D$16
A7: Ending cash | B7: =B4+B5-B6 | C7: =C4+C5-C6 | D7: =D4+D5-D6
A8: Minimum cash | B8: =MIN(B4,B7) | C8: =MIN(C4,C7) | D8: =MIN(D4,D7)
A9: Weeks below buffer | B9: =IF(B7<Assumptions!B$7,1,0) | C9: =IF(C7<Assumptions!C$7,1,0) | D9: =IF(D7<Assumptions!D$7,1,0)
A10: Ending runway | B10: =IF((Assumptions!B$8+Assumptions!B$11+Assumptions!B$12*Assumptions!B$14*Assumptions!B$9+Assumptions!B$12*Assumptions!B$14*(1-Assumptions!B$9)*Assumptions!B$10)=0,999,B7/(Assumptions!B$8+Assumptions!B$11+Assumptions!B$12*Assumptions!B$14*Assumptions!B$9+Assumptions!B$12*Assumptions!B$14*(1-Assumptions!B$9)*Assumptions!B$10)) | C10: =IF((Assumptions!C$8+Assumptions!C$11+Assumptions!C$12*Assumptions!C$14*Assumptions!C$9+Assumptions!C$12*Assumptions!C$14*(1-Assumptions!C$9)*Assumptions!C$10)=0,999,C7/(Assumptions!C$8+Assumptions!C$11+Assumptions!C$12*Assumptions!C$14*Assumptions!C$9+Assumptions!C$12*Assumptions!C$14*(1-Assumptions!C$9)*Assumptions!C$10)) | D10: =IF((Assumptions!D$8+Assumptions!D$11+Assumptions!D$12*Assumptions!D$14*Assumptions!D$9+Assumptions!D$12*Assumptions!D$14*(1-Assumptions!D$9)*Assumptions!D$10)=0,999,D7/(Assumptions!D$8+Assumptions!D$11+Assumptions!D$12*Assumptions!D$14*Assumptions!D$9+Assumptions!D$12*Assumptions!D$14*(1-Assumptions!D$9)*Assumptions!D$10))
A11: Status | B11: =IF(B7<Assumptions!B$7,"At Risk",IF(B10<Assumptions!B$17,"Watch","Healthy")) | C11: =IF(C7<Assumptions!C$7,"At Risk",IF(C10<Assumptions!C$17,"Watch","Healthy")) | D11: =IF(D7<Assumptions!D$7,"At Risk",IF(D10<Assumptions!D$17,"Watch","Healthy"))

Sheet Checks
A1: Model Checks
A3: Check | B3: Result | C3: Detail | D3: Formula / Logic
A4: Opening cash flows to forecast | B4: =IF('13-Week Forecast'!B4=Assumptions!$E$6,"PASS","FAIL") | C4: ='13-Week Forecast'!B4-Assumptions!$E$6 | D4: Week 1 opening cash equals active scenario opening cash
A5: Closing cash roll-forward | B5: =IF(SUMPRODUCT(ABS('13-Week Forecast'!B13:N13-('13-Week Forecast'!B4:N4+'13-Week Forecast'!B12:N12)))<0.01,"PASS","FAIL") | C5: =SUMPRODUCT(ABS('13-Week Forecast'!B13:N13-('13-Week Forecast'!B4:N4+'13-Week Forecast'!B12:N12))) | D5: Closing cash = opening cash + net cash flow
A6: No negative receipts | B6: =IF(MIN('13-Week Forecast'!B5:N5)>=0,"PASS","FAIL") | C6: =MIN('13-Week Forecast'!B5:N5) | D6: Receipts cannot be negative
A7: Tax reserve non-negative | B7: =IF(MIN('13-Week Forecast'!B8:N8)>=0,"PASS","FAIL") | C7: =MIN('13-Week Forecast'!B8:N8) | D7: Tax reserve floors at zero
A8: Scenario selection valid | B8: =IF(COUNTIF(Assumptions!$B$20:$D$20,Scenario_Selected)=1,"PASS","FAIL") | C8: =Scenario_Selected | D8: Dropdown must match scenario list
A10: Overall model status | B10: =IF(COUNTIF(B4:B8,"FAIL")=0,"PASS","FAIL")
